django_site_warnings/__init__.py
django_site_warnings/actions.py
django_site_warnings/admin.py
django_site_warnings/apps.py
django_site_warnings/global_sidebar.py
django_site_warnings/models.py
django_site_warnings/tests.py
django_site_warnings/views.py
django_site_warnings/locale/zh_Hans/LC_MESSAGES/django.mo
django_site_warnings/locale/zh_Hans/LC_MESSAGES/django.po
django_site_warnings/migrations/0001_initial.py
django_site_warnings/migrations/0002_auto_20210226_1541.py
django_site_warnings/migrations/0003_auto_20210226_1617.py
django_site_warnings/migrations/0004_auto_20210304_2119.py
django_site_warnings/migrations/0005_auto_20220310_1544.py
django_site_warnings/migrations/0006_auto_20231025_1637.py
django_site_warnings/migrations/0007_remove_warning_auto_reset_time_and_more.py
django_site_warnings/migrations/__init__.py
django_site_warnings/templates/django_site_warnings/notify.html
django_site_warnings-0.4.1.dist-info/licenses/LICENSE
django_site_warnings-0.4.1.dist-info/METADATA
django_site_warnings-0.4.1.dist-info/WHEEL
django_site_warnings-0.4.1.dist-info/top_level.txt
django_site_warnings-0.4.1.dist-info/RECORD
