Metadata-Version: 2.4
Name: django-site-warnings
Version: 0.4.1
Summary: 记录站点告警信息，提供告警确认等管理功能。
Author: Zhang YiLei
Maintainer: Zhang YiLei
License: Mulan PSL v2
Keywords: django extentions
Classifier: Development Status :: 5 - Production/Stable
Classifier: Intended Audience :: Developers
Classifier: Topic :: Software Development :: Libraries :: Python Modules
Classifier: Programming Language :: Python :: 3
Classifier: Programming Language :: Python :: 3 :: Only
License-File: LICENSE
Requires-Dist: django
Requires-Dist: django-safe-fields
Requires-Dist: django-import-export
Requires-Dist: django-model-helper
Requires-Dist: zenutils
Dynamic: author
Dynamic: classifier
Dynamic: description
Dynamic: description-content-type
Dynamic: keywords
Dynamic: license
Dynamic: license-file
Dynamic: maintainer
Dynamic: requires-dist
Dynamic: summary
